[
  {
    "map": "62-1",
    "difficulty": 1,
    "rewards": [
      { "api_id": 54, "api_type": 1, "api_value": 1 },
      { "api_id": 111, "api_type": 7, "api_value": 1 },
      { "api_id": 112, "api_type": 7, "api_value": 1 }
    ],
    "selectreward": {
      "111": [
        { "api_id": 902, "api_type": 1, "api_value": 1, "api_item_no": 1 },
        { "api_id": 3, "api_type": 1, "api_value": 20, "api_item_no": 2 }
      ],
      "112": [
        { "api_id": 104, "api_type": 1, "api_value": 1, "api_item_no": 1 },
        { "api_id": 51, "api_type": 1, "api_value": 1, "api_item_no": 2 }
      ]
    }
  },
  {
    "map": "62-1",
    "difficulty": 2,
    "rewards": [
      { "api_id": 54, "api_type": 1, "api_value": 1 },
      { "api_id": 121, "api_type": 7, "api_value": 1 },
      { "api_id": 122, "api_type": 7, "api_value": 1 },
      { "api_id": 123, "api_type": 7, "api_value": 1 },
      { "api_id": 379, "api_type": 3, "api_value": 1 }
    ],
    "selectreward": {
      "121": [
        { "api_id": 903, "api_type": 1, "api_value": 1, "api_item_no": 1 },
        { "api_id": 3, "api_type": 1, "api_value": 30, "api_item_no": 2 }
      ],
      "122": [
        { "api_id": 104, "api_type": 1, "api_value": 1, "api_item_no": 1 },
        { "api_id": 51, "api_type": 1, "api_value": 1, "api_item_no": 2 }
      ],
      "123": [
        { "api_id": 31, "api_type": 1, "api_value": 1600, "api_item_no": 1 },
        { "api_id": 59, "api_type": 1, "api_value": 1, "api_item_no": 2 }
      ]
    }
  },
  {
    "map": "62-1",
    "difficulty": 3,
    "rewards": [
      { "api_id": 54, "api_type": 1, "api_value": 2 },
      { "api_id": 131, "api_type": 7, "api_value": 1 },
      { "api_id": 132, "api_type": 7, "api_value": 1 },
      { "api_id": 133, "api_type": 7, "api_value": 1 },
      { "api_id": 379, "api_type": 3, "api_value": 1 },
      { "api_id": 572, "api_type": 3, "api_value": 1 }
    ],
    "selectreward": {
      "131": [
        { "api_id": 904, "api_type": 1, "api_value": 1, "api_item_no": 1 },
        { "api_id": 3, "api_type": 1, "api_value": 35, "api_item_no": 2 }
      ],
      "132": [
        { "api_id": 104, "api_type": 1, "api_value": 1, "api_item_no": 1 },
        { "api_id": 51, "api_type": 1, "api_value": 1, "api_item_no": 2 }
      ],
      "133": [
        { "api_id": 31, "api_type": 1, "api_value": 3200, "api_item_no": 1 },
        { "api_id": 59, "api_type": 1, "api_value": 2, "api_item_no": 2 }
      ]
    }
  },
  {
    "map": "62-1",
    "difficulty": 4,
    "rewards": [
      { "api_id": 57, "api_type": 1, "api_value": 1 },
      { "api_id": 54, "api_type": 1, "api_value": 3 },
      { "api_id": 141, "api_type": 7, "api_value": 1 },
      { "api_id": 142, "api_type": 7, "api_value": 1 },
      { "api_id": 143, "api_type": 7, "api_value": 1 },
      { "api_id": 379, "api_type": 3, "api_value": 1 },
      { "api_id": 575, "api_type": 3, "api_value": 1, "api_slot_level": 1 },
      { "api_id": 572, "api_type": 3, "api_value": 1, "api_slot_level": 2 }
    ],
    "selectreward": {
      "141": [
        { "api_id": 905, "api_type": 1, "api_value": 1, "api_item_no": 1 },
        { "api_id": 3, "api_type": 1, "api_value": 45, "api_item_no": 2 }
      ],
      "142": [
        { "api_id": 104, "api_type": 1, "api_value": 2, "api_item_no": 1 },
        { "api_id": 51, "api_type": 1, "api_value": 1, "api_item_no": 2 }
      ],
      "143": [
        { "api_id": 31, "api_type": 1, "api_value": 4800, "api_item_no": 1 },
        { "api_id": 59, "api_type": 1, "api_value": 3, "api_item_no": 2 }
      ]
    }
  },
  { "map": "62-2", "difficulty": 1, "rewards": [{ "api_id": 991, "api_type": 2, "api_value": 1 }], "selectreward": null },
  {
    "map": "62-2",
    "difficulty": 2,
    "rewards": [
      { "api_id": 578, "api_type": 3, "api_value": 1, "api_slot_level": 4 },
      { "api_id": 525, "api_type": 3, "api_value": 1 },
      { "api_id": 94, "api_type": 1, "api_value": 1 },
      { "api_id": 991, "api_type": 2, "api_value": 1 }
    ],
    "selectreward": null
  },
  {
    "map": "62-2",
    "difficulty": 3,
    "rewards": [
      { "api_id": 57, "api_type": 1, "api_value": 1 },
      { "api_id": 578, "api_type": 3, "api_value": 1, "api_slot_level": 7 },
      { "api_id": 231, "api_type": 7, "api_value": 1 },
      { "api_id": 526, "api_type": 3, "api_value": 1 },
      { "api_id": 307, "api_type": 3, "api_value": 1 },
      { "api_id": 991, "api_type": 2, "api_value": 1 }
    ],
    "selectreward": {
      "231": [
        { "api_id": 532, "api_type": 3, "api_value": 1, "api_item_no": 1 },
        { "api_id": 94, "api_type": 1, "api_value": 2, "api_item_no": 2 }
      ]
    }
  },
  {
    "map": "62-2",
    "difficulty": 4,
    "rewards": [
      { "api_id": 57, "api_type": 1, "api_value": 2 },
      { "api_id": 4, "api_type": 1, "api_value": 6 },
      { "api_id": 578, "api_type": 3, "api_value": 1, "api_slot_level": 9 },
      { "api_id": 241, "api_type": 7, "api_value": 1 },
      { "api_id": 218, "api_type": 3, "api_value": 1, "api_slot_level": 6 },
      { "api_id": 526, "api_type": 3, "api_value": 1, "api_slot_level": 3 },
      { "api_id": 307, "api_type": 3, "api_value": 1 },
      { "api_id": 991, "api_type": 2, "api_value": 1 }
    ],
    "selectreward": {
      "241": [
        { "api_id": 532, "api_type": 3, "api_value": 1, "api_item_no": 1 },
        { "api_id": 94, "api_type": 1, "api_value": 3, "api_item_no": 2 }
      ]
    }
  },
  { "map": "62-3", "difficulty": 1, "rewards": [{ "api_id": 1023, "api_type": 2, "api_value": 1 }], "selectreward": null },
  {
    "map": "62-3",
    "difficulty": 2,
    "rewards": [
      { "api_id": 57, "api_type": 1, "api_value": 1 },
      { "api_id": 4, "api_type": 1, "api_value": 5 },
      { "api_id": 321, "api_type": 7, "api_value": 1 },
      { "api_id": 1023, "api_type": 2, "api_value": 1 }
    ],
    "selectreward": {
      "321": [
        { "api_id": 146, "api_type": 3, "api_value": 3, "api_item_no": 1 },
        { "api_id": 100, "api_type": 1, "api_value": 1, "api_item_no": 2 }
      ]
    }
  },
  {
    "map": "62-3",
    "difficulty": 3,
    "rewards": [
      { "api_id": 57, "api_type": 1, "api_value": 2 },
      { "api_id": 4, "api_type": 1, "api_value": 6 },
      { "api_id": 331, "api_type": 7, "api_value": 1 },
      { "api_id": 577, "api_type": 3, "api_value": 1, "api_slot_level": 4 },
      { "api_id": 256, "api_type": 3, "api_value": 1, "api_slot_level": 2 },
      { "api_id": 1023, "api_type": 2, "api_value": 1 }
    ],
    "selectreward": {
      "331": [
        { "api_id": 146, "api_type": 3, "api_value": 4, "api_item_no": 1 },
        { "api_id": 100, "api_type": 1, "api_value": 2, "api_item_no": 2 }
      ]
    }
  },
  {
    "map": "62-3",
    "difficulty": 4,
    "rewards": [
      { "api_id": 57, "api_type": 1, "api_value": 3 },
      { "api_id": 4, "api_type": 1, "api_value": 8 },
      { "api_id": 341, "api_type": 7, "api_value": 1 },
      { "api_id": 64, "api_type": 1, "api_value": 1 },
      { "api_id": 577, "api_type": 3, "api_value": 1, "api_slot_level": 8 },
      { "api_id": 256, "api_type": 3, "api_value": 1, "api_slot_level": 7 },
      { "api_id": 375, "api_type": 3, "api_value": 1, "api_slot_level": 1 },
      { "api_id": 1023, "api_type": 2, "api_value": 1 }
    ],
    "selectreward": {
      "341": [
        { "api_id": 146, "api_type": 3, "api_value": 6, "api_item_no": 1 },
        { "api_id": 100, "api_type": 1, "api_value": 3, "api_item_no": 2 }
      ]
    }
  },
  { "map": "62-4", "difficulty": 1, "rewards": [{ "api_id": 1051, "api_type": 2, "api_value": 1 }], "selectreward": null },
  {
    "map": "62-4",
    "difficulty": 4,
    "rewards": [
      { "api_id": 57, "api_type": 1, "api_value": 2 },
      { "api_id": 105, "api_type": 1, "api_value": 7 },
      { "api_id": 441, "api_type": 7, "api_value": 1 },
      { "api_id": 581, "api_type": 3, "api_value": 1, "api_slot_level": 2 },
      { "api_id": 78, "api_type": 1, "api_value": 1 },
      { "api_id": 576, "api_type": 3, "api_value": 1, "api_slot_level": 2 },
      { "api_id": 442, "api_type": 7, "api_value": 1 },
      { "api_id": 583, "api_type": 3, "api_value": 1, "api_slot_level": 3 },
      { "api_id": 1051, "api_type": 2, "api_value": 1 }
    ],
    "selectreward": {
      "441": [
        { "api_id": 105, "api_type": 1, "api_value": 3, "api_item_no": 1 },
        { "api_id": 585, "api_type": 3, "api_value": 1, "api_item_no": 2, "api_slot_level": 6 }
      ],
      "442": [
        { "api_id": 579, "api_type": 3, "api_value": 1, "api_item_no": 1, "api_slot_level": 6 },
        { "api_id": 497, "api_type": 3, "api_value": 1, "api_item_no": 2, "api_slot_level": 6 }
      ]
    }
  },
  {
    "map": "62-5",
    "difficulty": 4,
    "rewards": [
      { "api_id": 57, "api_type": 1, "api_value": 3 },
      { "api_id": 4, "api_type": 1, "api_value": 10 },
      { "api_id": 541, "api_type": 7, "api_value": 1 },
      { "api_id": 542, "api_type": 7, "api_value": 1 },
      { "api_id": 101, "api_type": 1, "api_value": 1 },
      { "api_id": 476, "api_type": 3, "api_value": 1, "api_slot_level": 1 },
      { "api_id": 543, "api_type": 7, "api_value": 1 },
      { "api_id": 61, "api_type": 1, "api_value": 1 },
      { "api_id": 1055, "api_type": 2, "api_value": 1 }
    ],
    "selectreward": {
      "541": [
        { "api_id": 105, "api_type": 1, "api_value": 3, "api_item_no": 1 },
        { "api_id": 584, "api_type": 3, "api_value": 1, "api_item_no": 2, "api_slot_level": 4 }
      ],
      "542": [
        { "api_id": 105, "api_type": 1, "api_value": 4, "api_item_no": 1 },
        { "api_id": 587, "api_type": 3, "api_value": 1, "api_item_no": 2, "api_slot_level": 4 }
      ],
      "543": [
        { "api_id": 588, "api_type": 3, "api_value": 1, "api_item_no": 1, "api_slot_level": 5 },
        { "api_id": 100, "api_type": 1, "api_value": 5, "api_item_no": 2 }
      ]
    }
  }
]
