{
  "1": [
    { "no": 0, "x": 446, "y": 137, "direction": "L" },
    { "no": 1, "x": 213, "y": 266, "line": { "x": 22, "y": -49 }, "offsets": { "10": { "x": 10, "y": -8 } }, "color": -1, "direction": "L" },
    { "no": 2, "x": 249, "y": 384, "line": { "x": -30, "y": -91 } },
    { "no": 3, "x": 322, "y": 206, "line": { "x": 24, "y": -50 }, "direction": "L" },
    { "no": 4, "x": 368, "y": 353, "line": { "x": -132, "y": -77 } },
    { "no": 5, "x": 408, "y": 247, "line": { "x": 5, "y": -64 }, "direction": "L" },
    { "no": 6, "x": 427, "y": 518, "line": { "x": -49, "y": -138 } },
    { "no": 7, "x": 494, "y": 421, "line": { "x": -104, "y": -59 } },
    { "no": 8, "x": 524, "y": 300, "line": { "x": -97, "y": -47 } },
    { "no": 9, "x": 606, "y": 483, "line": { "x": -93, "y": -53 }, "offsets": { "10": { "x": 9, "y": -6 } }, "color": -1 },
    { "no": 10, "x": 296, "y": 502, "line": { "x": 31, "y": -7 }, "direction": "L" },
    { "no": 11, "x": 368, "y": 353, "line": { "x": -93, "y": 3 } },
    { "no": 12, "x": 368, "y": 353, "line": { "x": -40, "y": -121 } },
    { "no": 13, "x": 368, "y": 353, "line": { "x": 7, "y": -86 }, "direction": "L" },
    { "no": 14, "x": 427, "y": 518, "line": { "x": 11, "y": -77 }, "direction": "L" },
    { "no": 15, "x": 742, "y": 372, "route": { "img": "route_15_1" }, "line": { "x": -119, "y": 15 }, "color": -1 },
    { "no": 16, "x": 823, "y": 374, "route": { "img": "route_16_1" }, "line": { "x": -23, "y": -27 }, "color": -1 },
    { "no": 17, "x": 876, "y": 393, "route": { "img": "route_17_1" }, "line": { "x": -36, "y": -14 }, "color": -1 },
    { "no": 18, "x": 882, "y": 447, "route": { "img": "route_18_1" }, "line": { "x": -7, "y": -35 }, "color": -1 },
    {
      "no": 19,
      "x": 939,
      "y": 450,
      "route": { "img": "route_19_1" },
      "line": { "x": -49, "y": -44 },
      "offsets": { "10": { "x": 11, "y": -5 } },
      "color": -1
    },
    { "no": 20, "x": 950, "y": 509, "route": { "img": "route_20_1" }, "line": { "x": -10, "y": -38 }, "color": -1 },
    { "no": 21, "x": 1025, "y": 540, "route": { "img": "route_21_1" }, "line": { "x": -61, "y": -33 }, "color": -2 },
    {
      "no": 22,
      "x": 939,
      "y": 450,
      "route": { "img": "route_22_1" },
      "line": { "x": -36, "y": -4 },
      "offsets": { "10": { "x": 11, "y": -5 } },
      "color": -1
    },
    { "no": 23, "x": 788, "y": 317, "color": -3 },
    {
      "no": 24,
      "x": 487,
      "y": 224,
      "route": { "img": "route_24_1" },
      "line": { "x": -29, "y": -57 },
      "offsets": { "10": { "x": 10, "y": -6 } },
      "color": -1
    },
    {
      "no": 25,
      "x": 621,
      "y": 365,
      "route": { "img": "route_25_1" },
      "comment": { "type": "R", "x": 12, "y": 0 },
      "line": { "x": -14, "y": 25 },
      "color": -1
    },
    { "no": 26, "x": 642, "y": 182, "route": { "img": "route_26_1" }, "line": { "x": 16, "y": 23 }, "color": -1, "direction": "L" },
    { "no": 27, "x": 715, "y": 298, "route": { "img": "route_27_1" }, "line": { "x": -76, "y": 10 }, "color": -1 },
    { "no": 28, "x": 632, "y": 272, "route": { "img": "route_28_1" }, "line": { "x": -21, "y": 34 }, "color": -2 },
    { "no": 29, "x": 632, "y": 272, "route": { "img": "route_29_1" }, "line": { "x": 32, "y": 6 }, "color": -2, "direction": "L" },
    { "no": 30, "x": 368, "y": 353, "route": { "img": "route_30_1" }, "line": { "x": 20, "y": -50 }, "color": -1, "direction": "L" },
    { "no": 31, "x": 524, "y": 300, "route": { "img": "route_31_1" }, "line": { "x": -31, "y": -58 }, "color": -1 },
    {
      "no": 32,
      "x": 606,
      "y": 483,
      "route": { "img": "route_32_1" },
      "line": { "x": -75, "y": -159 },
      "offsets": { "10": { "x": 9, "y": -6 } },
      "color": -1
    },
    { "no": -1, "x": 835, "y": 265 }
  ],
  "2": [
    { "no": 0, "x": 161, "y": 205 },
    { "no": 1, "x": 226, "y": 263, "line": { "x": -31, "y": -28 } },
    { "no": 2, "x": 310, "y": 336, "line": { "x": -69, "y": -61 }, "offsets": { "10": { "x": 10, "y": -7 } }, "color": -1 },
    { "no": 3, "x": 399, "y": 273, "line": { "x": 19, "y": 17 }, "color": -1, "direction": "L" },
    { "no": 4, "x": 407, "y": 363, "line": { "x": -66, "y": -21 }, "branch": { "type": "T", "x": -5, "y": -20, "beak": "straight" } },
    { "no": 5, "x": 416, "y": 429, "line": { "x": -91, "y": -80 } },
    { "no": 6, "x": 453, "y": 320, "line": { "x": -31, "y": 13 } },
    { "no": 7, "x": 581, "y": 172, "line": { "x": -84, "y": -20 } },
    { "no": 8, "x": 586, "y": 420, "line": { "x": -159, "y": -52 } },
    { "no": 9, "x": 636, "y": 348, "line": { "x": -40, "y": 14 } },
    { "no": 10, "x": 689, "y": 387, "line": { "x": -84, "y": 2 }, "landing": { "x": 23, "y": -10 }, "comment": { "type": "LT" } },
    { "no": 11, "x": 709, "y": 198, "line": { "x": -110, "y": -25 }, "offsets": { "10": { "x": 8, "y": -4 } }, "color": -1 },
    { "no": 12, "x": 747, "y": 304, "line": { "x": -50, "y": 16 } },
    { "no": 13, "x": 805, "y": 254, "line": { "x": -80, "y": -46 } },
    { "no": 14, "x": 842, "y": 180, "line": { "x": -114, "y": 1 }, "offsets": { "10": { "x": 10, "y": -4 } }, "color": -1 },
    { "no": 15, "x": 955, "y": 164, "line": { "x": -90, "y": -1 } },
    { "no": 16, "x": 970, "y": 311, "line": { "x": -117, "y": -115 } },
    { "no": 17, "x": 770, "y": 459, "line": { "x": -67, "y": -60 } },
    { "no": 18, "x": 586, "y": 420, "line": { "x": -144, "y": 0 } },
    { "no": 19, "x": 689, "y": 387, "line": { "x": -36, "y": -26 } },
    { "no": 20, "x": 747, "y": 304, "line": { "x": -35, "y": -85 } },
    { "no": 21, "x": 842, "y": 180, "line": { "x": -29, "y": 18 }, "offsets": { "10": { "x": 10, "y": -4 } }, "color": -1 },
    { "no": 22, "x": 970, "y": 311, "line": { "x": -18, "y": -125 } },
    { "no": 23, "x": 457, "y": 146, "color": -3 },
    {
      "no": 24,
      "x": 916,
      "y": 384,
      "route": { "img": "route_24_1" },
      "line": { "x": 11, "y": -54 },
      "offsets": { "10": { "x": 10, "y": 3 } },
      "color": -1,
      "direction": "L"
    },
    { "no": 25, "x": 976, "y": 489, "route": { "img": "route_25_1" }, "line": { "x": 16, "y": -46 }, "color": -1, "direction": "L" },
    {
      "no": 26,
      "x": 1032,
      "y": 427,
      "route": { "img": "route_26_1" },
      "line": { "x": -55, "y": -100 },
      "offsets": { "10": { "x": 6, "y": -5 } },
      "color": -1
    },
    { "no": 27, "x": 851, "y": 486, "route": { "img": "route_27_1" }, "line": { "x": 34, "y": -54 }, "color": -2, "direction": "L" },
    {
      "no": 28,
      "x": 1032,
      "y": 427,
      "route": { "img": "route_28_1" },
      "line": { "x": -92, "y": -35 },
      "offsets": { "10": { "x": 6, "y": -5 } },
      "color": -1
    },
    {
      "no": 29,
      "x": 363,
      "y": 536,
      "route": { "img": "route_29_1" },
      "line": { "x": -80, "y": -93 },
      "offsets": { "10": { "x": 10, "y": -5 } },
      "color": -1
    },
    { "no": 30, "x": 483, "y": 528, "route": { "img": "route_30_1" }, "line": { "x": -93, "y": -3 }, "color": -1 },
    { "no": 31, "x": 573, "y": 487, "route": { "img": "route_31_1" }, "line": { "x": -65, "y": 7 }, "color": -1 },
    { "no": 32, "x": 654, "y": 449, "route": { "img": "route_32_1" }, "line": { "x": -60, "y": 6 }, "color": -1 },
    {
      "no": 33,
      "x": 728,
      "y": 509,
      "route": { "img": "route_33_1" },
      "line": { "x": -219, "y": 0 },
      "offsets": { "10": { "x": 8, "y": 3 } },
      "color": -1
    },
    {
      "no": 34,
      "x": 920,
      "y": 545,
      "route": { "img": "route_34_1" },
      "line": { "x": -168, "y": -34 },
      "replenish": { "box": { "x": 0, "y": 0 }, "btn": { "x": 0, "y": -34 } },
      "ration": { "box": { "x": 0, "y": 0 }, "btn": { "x": 0, "y": -34 } },
      "comment": { "type": "LT", "x": -37, "y": 28 },
      "color": -1
    },
    { "no": 35, "x": 1030, "y": 539, "route": { "img": "route_35_1" }, "line": { "x": -88, "y": -9 }, "color": -2 },
    { "no": 36, "x": 483, "y": 528, "route": { "img": "route_36_1" }, "line": { "x": -194, "y": -108 }, "color": -1 },
    {
      "no": 37,
      "x": 728,
      "y": 509,
      "route": { "img": "route_37_1" },
      "line": { "x": -57, "y": -45 },
      "offsets": { "10": { "x": 8, "y": 3 } },
      "color": -1
    },
    { "no": 38, "x": 770, "y": 459, "route": { "img": "route_38_1" }, "line": { "x": -94, "y": -17 }, "color": -2 },
    { "no": 39, "x": 976, "y": 489, "route": { "img": "route_39_1" }, "line": { "x": -45, "y": 17 }, "color": -1 },
    { "no": 40, "x": 253, "y": 403, "color": -3 },
    { "no": -1, "x": 100, "y": 123 }
  ],
  "3": [
    { "no": 0, "x": 243, "y": 222 },
    { "no": 1, "x": 317, "y": 274, "line": { "x": -37, "y": -26 } },
    { "no": 2, "x": 395, "y": 331, "line": { "x": -57, "y": -43 }, "offsets": { "10": { "x": 10, "y": -7 } }, "color": -1 },
    { "no": 3, "x": 415, "y": 159, "line": { "x": -82, "y": 20 } },
    { "no": 4, "x": 465, "y": 380, "line": { "x": -51, "y": -42 } },
    { "no": 5, "x": 554, "y": 159, "line": { "x": -117, "y": -4 }, "offsets": { "10": { "x": 14, "y": -7 } }, "color": -1 },
    { "no": 6, "x": 570, "y": 345, "line": { "x": 6, "y": -63 } },
    { "no": 7, "x": 599, "y": 259, "line": { "x": -156, "y": -83 }, "offsets": { "10": { "x": 8, "y": -5 } }, "color": -1 },
    { "no": 8, "x": 643, "y": 492, "line": { "x": -68, "y": -127 }, "offsets": { "10": { "x": 6, "y": -7 } }, "color": -1 },
    { "no": 9, "x": 690, "y": 401, "line": { "x": -104, "y": -47 } },
    { "no": 10, "x": 767, "y": 435, "line": { "x": -59, "y": -28 } },
    { "no": 11, "x": 780, "y": 524, "line": { "x": -114, "y": -28 } },
    { "no": 12, "x": 846, "y": 470, "line": { "x": -60, "y": -29 }, "color": -1 },
    { "no": 13, "x": 928, "y": 495, "line": { "x": -62, "y": -21 }, "comment": { "type": "LT" }, "landing": { "x": 19, "y": 48 } },
    { "no": 14, "x": 929, "y": 436, "line": { "x": -15, "y": 18 }, "color": -2 },
    { "no": 15, "x": 599, "y": 259, "line": { "x": -38, "y": -82 }, "offsets": { "10": { "x": 8, "y": -5 } }, "color": -1 },
    { "no": 16, "x": 846, "y": 470, "line": { "x": -49, "y": 12 }, "color": -1 },
    { "no": 17, "x": 272, "y": 400, "route": { "img": "route_17_1" }, "line": { "x": 20, "y": -59 }, "color": -1 },
    { "no": 18, "x": 412, "y": 479, "route": { "img": "route_18_1" }, "line": { "x": -18, "y": -120 }, "color": -1 },
    {
      "no": 19,
      "x": 555,
      "y": 443,
      "route": { "img": "route_19_1" },
      "line": { "x": -70, "y": -52 },
      "offsets": { "10": { "x": 7, "y": -6 } },
      "color": -1
    },
    { "no": 20, "x": 579, "y": 528, "route": { "img": "route_20_1" }, "line": { "x": -147, "y": -45 }, "color": -1 },
    { "no": 21, "x": 292, "y": 315, "route": { "img": "route_21_1" }, "line": { "x": -44, "y": -11 }, "color": -1 },
    { "no": 22, "x": 412, "y": 479, "route": { "img": "route_22_1" }, "line": { "x": -123, "y": -71 }, "color": -1 },
    {
      "no": 23,
      "x": 395,
      "y": 331,
      "route": { "img": "route_23_1" },
      "line": { "x": -76, "y": -15 },
      "offsets": { "10": { "x": 10, "y": -7 } },
      "color": -1
    },
    { "no": 24, "x": 202, "y": 298, "color": -3 },
    {
      "no": 25,
      "x": 716,
      "y": 261,
      "route": { "img": "route_25_1" },
      "line": { "x": -91, "y": -5 },
      "branch": { "type": "T", "x": -5, "y": -26, "beak": "straight" },
      "color": -1
    },
    { "no": 26, "x": 778, "y": 203, "route": { "img": "route_26_1" }, "line": { "x": -47, "y": 11 }, "color": -1 },
    { "no": 27, "x": 798, "y": 298, "route": { "img": "route_27_1" }, "line": { "x": -60, "y": -30 }, "color": -1 },
    {
      "no": 28,
      "x": 840,
      "y": 137,
      "route": { "img": "route_28_1" },
      "line": { "x": -49, "y": 16 },
      "offsets": { "10": { "x": 10, "y": -3 } },
      "color": -1
    },
    {
      "no": 29,
      "x": 877,
      "y": 335,
      "route": { "img": "route_29_1" },
      "line": { "x": -61, "y": -30 },
      "offsets": { "10": { "x": 10, "y": -5 } },
      "comment": { "type": "LT" },
      "color": -1
    },
    { "no": 30, "x": 896, "y": 238, "route": { "img": "route_30_1" }, "line": { "x": -92, "y": -29 }, "color": -1 },
    { "no": 31, "x": 970, "y": 380, "route": { "img": "route_31_1" }, "line": { "x": -74, "y": -38 }, "color": -1 },
    { "no": 32, "x": 1003, "y": 153, "route": { "img": "route_32_1" }, "line": { "x": -89, "y": 15 }, "color": -1 },
    { "no": 33, "x": 1013, "y": 271, "route": { "img": "route_33_1" }, "line": { "x": -113, "y": 15 }, "color": -2 },
    { "no": 34, "x": 896, "y": 238, "route": { "img": "route_34_1" }, "line": { "x": -46, "y": -81 }, "color": -1 },
    { "no": 35, "x": 896, "y": 238, "route": { "img": "route_35_1" }, "line": { "x": -16, "y": 26 }, "color": -1 },
    { "no": 36, "x": 1013, "y": 271, "route": { "img": "route_36_1" }, "line": { "x": -96, "y": -31 }, "color": -2 },
    { "no": 37, "x": 824, "y": 409, "route": { "img": "route_37_1" }, "line": { "x": -113, "y": -11 }, "color": -1 },
    { "no": 38, "x": 995, "y": 444, "route": { "img": "route_38_1" }, "line": { "x": -51, "y": 15 }, "color": -1 },
    { "no": 39, "x": 988, "y": 505, "route": { "img": "route_39_1" }, "line": { "x": -47, "y": -21 }, "color": -2 },
    { "no": 40, "x": 846, "y": 470, "route": { "img": "route_40_1" }, "line": { "x": -16, "y": -38 }, "color": -1 },
    { "no": 41, "x": 928, "y": 495, "route": { "img": "route_41_1" }, "line": { "x": -88, "y": -76 }, "color": -1 },
    { "no": -1, "x": 193, "y": 143 }
  ],
  "4": [
    { "no": 0, "x": 517, "y": 262 },
    { "no": 1, "x": 609, "y": 302, "line": { "x": -59, "y": -30 }, "offsets": { "10": { "x": 11, "y": 1 } }, "color": -1 },
    { "no": 2, "x": 631, "y": 197, "line": { "x": -79, "y": 9 } },
    { "no": 3, "x": 736, "y": 198, "line": { "x": -86, "y": -4 } },
    { "no": 4, "x": 752, "y": 264, "line": { "x": -103, "y": -56 }, "offsets": { "10": { "x": 0, "y": -1 } }, "color": -1 },
    { "no": 5, "x": 771, "y": 345, "line": { "x": -18, "y": -62 } },
    { "no": 6, "x": 826, "y": 198, "line": { "x": -71, "y": -15 }, "offsets": { "10": { "x": 9, "y": -1 } }, "color": -1 },
    { "no": 7, "x": 833, "y": 357, "line": { "x": -40, "y": -11 }, "offsets": { "10": { "x": 8, "y": -5 } }, "color": -1 },
    { "no": 8, "x": 853, "y": 282, "line": { "x": -80, "y": -22 } },
    { "no": 9, "x": 917, "y": 377, "line": { "x": -62, "y": -17 }, "comment": { "type": "LT" } },
    { "no": 10, "x": 926, "y": 431, "line": { "x": -9, "y": -35 } },
    { "no": 11, "x": 983, "y": 378, "line": { "x": -40, "y": -3 }, "color": -1 },
    { "no": 12, "x": 1038, "y": 436, "line": { "x": -105, "y": -49 }, "color": -2 },
    { "no": 13, "x": 631, "y": 197, "line": { "x": -21, "y": 19 } },
    { "no": 14, "x": 752, "y": 264, "line": { "x": -13, "y": -42 }, "offsets": { "10": { "x": 0, "y": -1 } }, "color": -1 },
    { "no": 15, "x": 1038, "y": 436, "line": { "x": -93, "y": -11 }, "color": -2 },
    { "no": 16, "x": 1038, "y": 436, "line": { "x": -50, "y": -56 }, "color": -2 },
    { "no": 17, "x": 587, "y": 401, "route": { "img": "route_17_1" }, "line": { "x": -78, "y": -49 }, "color": -1 },
    { "no": 18, "x": 624, "y": 530, "route": { "img": "route_18_1" }, "line": { "x": -35, "y": -110 }, "color": -1 },
    {
      "no": 19,
      "x": 681,
      "y": 458,
      "route": { "img": "route_19_1" },
      "line": { "x": -74, "y": -47 },
      "offsets": { "10": { "x": 6, "y": -8 } },
      "color": -1
    },
    {
      "no": 20,
      "x": 709,
      "y": 530,
      "route": { "img": "route_20_1" },
      "line": { "x": -65, "y": -3 },
      "offsets": { "10": { "x": 10, "y": 1 } },
      "color": -1
    },
    {
      "no": 21,
      "x": 148,
      "y": 276,
      "route": { "img": "route_21_1" },
      "line": { "x": 9, "y": -57 },
      "offsets": { "10": { "x": 9, "y": -4 } },
      "color": -1
    },
    { "no": 22, "x": 199, "y": 203, "route": { "img": "route_22_1" }, "line": { "x": 22, "y": 3 }, "color": -1 },
    { "no": 23, "x": 284, "y": 228, "route": { "img": "route_23_1" }, "line": { "x": 22, "y": -30 }, "color": -1 },
    {
      "no": 24,
      "x": 179,
      "y": 368,
      "route": { "img": "route_24_1" },
      "line": { "x": -25, "y": -70 },
      "offsets": { "10": { "x": 4, "y": -15 } },
      "color": -1
    },
    { "no": 25, "x": 230, "y": 300, "route": { "img": "route_25_1" }, "line": { "x": -61, "y": -19 }, "color": -1 },
    {
      "no": 26,
      "x": 316,
      "y": 297,
      "route": { "img": "route_26_1" },
      "line": { "x": 15, "y": -71 },
      "offsets": { "10": { "x": 10, "y": 6 } },
      "color": -1
    },
    { "no": 27, "x": 267, "y": 398, "route": { "img": "route_27_1" }, "line": { "x": -65, "y": -25 }, "color": -1 },
    { "no": 28, "x": 387, "y": 445, "route": { "img": "route_28_1" }, "line": { "x": -101, "y": -41 }, "color": -1 },
    {
      "no": 29,
      "x": 240,
      "y": 442,
      "route": { "img": "route_29_1" },
      "line": { "x": 6, "y": -31 },
      "offsets": { "10": { "x": 18, "y": -2 } },
      "color": -1
    },
    {
      "no": 30,
      "x": 186,
      "y": 454,
      "route": { "img": "route_30_1" },
      "line": { "x": 18, "y": -10 },
      "landing": { "x": -32, "y": 5 },
      "comment": { "type": "LT" },
      "color": -1
    },
    { "no": 31, "x": 230, "y": 499, "route": { "img": "route_31_1" }, "line": { "x": -43, "y": -40 }, "color": -1 },
    { "no": 32, "x": 297, "y": 484, "route": { "img": "route_32_1" }, "line": { "x": -86, "y": -27 }, "color": -2 },
    {
      "no": 33,
      "x": 681,
      "y": 458,
      "route": { "img": "route_33_1" },
      "line": { "x": -48, "y": 16 },
      "offsets": { "10": { "x": 6, "y": -8 } },
      "color": -1
    },
    {
      "no": 34,
      "x": 681,
      "y": 458,
      "route": { "img": "route_34_1" },
      "line": { "x": 4, "y": 19 },
      "offsets": { "10": { "x": 6, "y": -8 } },
      "color": -1
    },
    {
      "no": 35,
      "x": 148,
      "y": 276,
      "route": { "img": "route_35_1" },
      "line": { "x": 24, "y": -41 },
      "offsets": { "10": { "x": 9, "y": -4 } },
      "color": -1
    },
    {
      "no": 36,
      "x": 179,
      "y": 368,
      "route": { "img": "route_36_1" },
      "line": { "x": 10, "y": -52 },
      "offsets": { "10": { "x": 4, "y": -15 } },
      "color": -1
    },
    { "no": 37, "x": 230, "y": 300, "route": { "img": "route_37_1" }, "line": { "x": 11, "y": -53 }, "color": -1 },
    { "no": 38, "x": 230, "y": 300, "route": { "img": "route_38_1" }, "line": { "x": 21, "y": -4 }, "color": -1 },
    { "no": 39, "x": 410, "y": 188, "direction": "L", "color": -3 },
    { "no": 40, "x": 476, "y": 333, "color": -3 },
    {
      "no": 41,
      "x": 427,
      "y": 528,
      "route": { "img": "route_41_1" },
      "line": { "x": -32, "y": -62 },
      "offsets": { "10": { "x": 15, "y": -7 } },
      "color": -1
    },
    { "no": 42, "x": 507, "y": 488, "route": { "img": "route_42_1" }, "line": { "x": -100, "y": -40 }, "color": -1 },
    { "no": 43, "x": 308, "y": 550, "route": { "img": "route_43_1" }, "line": { "x": 15, "y": -87 }, "color": -1 },
    { "no": 44, "x": 677, "y": 366, "route": { "img": "route_44_1" }, "line": { "x": 15, "y": 15 }, "color": -1 },
    { "no": 45, "x": 746, "y": 428, "route": { "img": "route_45_1" }, "line": { "x": 4, "y": -62 }, "comment": { "type": "LT" }, "color": -1 },
    {
      "no": 46,
      "x": 791,
      "y": 468,
      "route": { "img": "route_46_1" },
      "line": { "x": -31, "y": -26 },
      "offsets": { "10": { "x": 7, "y": 8 } },
      "color": -1
    },
    { "no": 47, "x": 823, "y": 411, "route": { "img": "route_47_1" }, "line": { "x": -57, "y": -5 }, "color": -1 },
    { "no": 48, "x": 308, "y": 550, "route": { "img": "route_48_1" }, "line": { "x": 22, "y": -23 }, "color": -1 },
    { "no": 49, "x": 823, "y": 411, "route": { "img": "route_49_1" }, "line": { "x": -36, "y": 17 }, "color": -1 },
    { "no": 50, "x": 901, "y": 164, "route": { "img": "route_50_1" }, "line": { "x": -57, "y": 6 }, "color": -1 },
    {
      "no": 51,
      "x": 944,
      "y": 298,
      "route": { "img": "route_51_1" },
      "line": { "x": -66, "y": -14 },
      "comment": { "type": "LB", "x": -5 },
      "color": -1
    },
    { "no": 52, "x": 971, "y": 132, "route": { "img": "route_52_1" }, "line": { "x": -52, "y": 6 }, "color": -1 },
    { "no": 53, "x": 1040, "y": 313, "route": { "img": "route_53_1" }, "line": { "x": -75, "y": -21 }, "color": -1 },
    { "no": 54, "x": 1047, "y": 255, "route": { "img": "route_54_1" }, "line": { "x": -84, "y": 4 }, "color": -1 },
    { "no": 55, "x": 1005, "y": 187, "route": { "img": "route_55_1" }, "line": { "x": -54, "y": 27 }, "color": -2 },
    { "no": 56, "x": 944, "y": 298, "route": { "img": "route_56_1" }, "line": { "x": -37, "y": -111 }, "color": -1 },
    { "no": 57, "x": 1005, "y": 187, "route": { "img": "route_57_1" }, "line": { "x": 13, "y": 28 }, "color": -2 },
    { "no": 58, "x": 853, "y": 282, "route": { "img": "route_58_1" }, "line": { "x": 8, "y": -90 }, "color": -1 },
    { "no": 59, "x": 796, "y": 530, "route": { "img": "route_59_1" }, "line": { "x": -99, "y": -64 }, "color": -1 },
    { "no": 60, "x": 876, "y": 513, "route": { "img": "route_60_1" }, "line": { "x": -60, "y": 3 }, "comment": { "type": "LB" }, "color": -1 },
    { "no": 61, "x": 1024, "y": 548, "route": { "img": "route_61_1" }, "line": { "x": -128, "y": -28 }, "color": -1 },
    { "no": 62, "x": 982, "y": 488, "route": { "img": "route_62_1" }, "line": { "x": -87, "y": 0 }, "color": -2 },
    { "no": 63, "x": 796, "y": 530, "route": { "img": "route_63_1" }, "line": { "x": -65, "y": -2 }, "color": -1 },
    { "no": 64, "x": 982, "y": 488, "route": { "img": "route_64_1" }, "line": { "x": -55, "y": -49 }, "color": -2 },
    { "no": 65, "x": 926, "y": 431, "route": { "img": "route_65_1" }, "line": { "x": -38, "y": 21 }, "color": -1 },
    { "no": -1, "x": 473, "y": 200 }
  ],
  "5": [
    { "no": 0, "x": 102, "y": 398 },
    { "no": 1, "x": 272, "y": 477, "line": { "x": -132, "y": -63 } },
    { "no": 2, "x": 349, "y": 356, "line": { "x": -66, "y": 19 }, "offsets": { "10": { "x": 8, "y": -5 } }, "color": -1 },
    { "no": 3, "x": 411, "y": 375, "line": { "x": -40, "y": -14 } },
    { "no": 4, "x": 430, "y": 515, "line": { "x": -137, "y": -34 } },
    { "no": 5, "x": 595, "y": 523, "line": { "x": -142, "y": -9 } },
    { "no": 6, "x": 685, "y": 453, "line": { "x": -74, "y": 11 } },
    { "no": 7, "x": 761, "y": 531, "line": { "x": -142, "y": -10 }, "offsets": { "10": { "x": 8, "y": -3 } }, "color": -1 },
    { "no": 8, "x": 796, "y": 467, "line": { "x": -90, "y": -14 } },
    { "no": 9, "x": 898, "y": 535, "line": { "x": -115, "y": -7 } },
    { "no": 10, "x": 936, "y": 484, "line": { "x": -115, "y": -17 }, "comment": { "type": "LT" } },
    { "no": 11, "x": 1033, "y": 529, "line": { "x": -77, "y": -38 } },
    { "no": 12, "x": 1051, "y": 425, "line": { "x": -96, "y": 12 }, "color": -2 },
    { "no": 13, "x": 430, "y": 515, "line": { "x": -19, "y": -116 } },
    { "no": 14, "x": 761, "y": 531, "line": { "x": -64, "y": -65 }, "offsets": { "10": { "x": 8, "y": -3 } }, "color": -1 },
    { "no": 15, "x": 936, "y": 484, "line": { "x": -27, "y": 15 } },
    { "no": 16, "x": 234, "y": 171, "route": { "img": "route_16_1" }, "line": { "x": -67, "y": -12 }, "color": -1 },
    { "no": 17, "x": 245, "y": 268, "route": { "img": "route_17_1" }, "line": { "x": -11, "y": -70 }, "color": -1 },
    {
      "no": 18,
      "x": 475,
      "y": 196,
      "route": { "img": "route_18_1" },
      "line": { "x": -210, "y": 3 },
      "offsets": { "10": { "x": 9, "y": 1 } },
      "color": -1
    },
    {
      "no": 19,
      "x": 512,
      "y": 245,
      "route": { "img": "route_19_1" },
      "line": { "x": -26, "y": -33 },
      "offsets": { "10": { "x": 10, "y": -5 } },
      "color": -1
    },
    { "no": 20, "x": 557, "y": 299, "route": { "img": "route_20_1" }, "line": { "x": -30, "y": -33 }, "color": -1 },
    { "no": 21, "x": 633, "y": 345, "route": { "img": "route_21_1" }, "line": { "x": 21, "y": -31 }, "color": -1 },
    {
      "no": 22,
      "x": 641,
      "y": 200,
      "route": { "img": "route_22_1" },
      "line": { "x": -141, "y": -4 },
      "branch": { "type": "RB", "x": 15, "y": 25 },
      "color": -1
    },
    { "no": 23, "x": 678, "y": 133, "route": { "img": "route_23_1" }, "line": { "x": -185, "y": 4 }, "color": -1 },
    { "no": 24, "x": 704, "y": 314, "route": { "img": "route_24_1" }, "line": { "x": -120, "y": -16 }, "comment": { "type": "LT" }, "color": -1 },
    {
      "no": 25,
      "x": 788,
      "y": 127,
      "route": { "img": "route_25_1" },
      "line": { "x": -87, "y": -4 },
      "offsets": { "10": { "x": 10, "y": 0 } },
      "color": -1
    },
    { "no": 26, "x": 855, "y": 200, "route": { "img": "route_26_1" }, "line": { "x": -192, "y": -3 }, "color": -1 },
    {
      "no": 27,
      "x": 895,
      "y": 122,
      "route": { "img": "route_27_1" },
      "line": { "x": -86, "y": -4 },
      "comment": { "type": "LT", "y": 20 },
      "color": -1
    },
    { "no": 28, "x": 990, "y": 194, "route": { "img": "route_28_1" }, "line": { "x": -111, "y": -12 }, "color": -1 },
    { "no": 29, "x": 1016, "y": 133, "route": { "img": "route_29_1" }, "line": { "x": -100, "y": -19 }, "color": -1 },
    { "no": 30, "x": 841, "y": 255, "route": { "img": "route_30_1" }, "line": { "x": 1, "y": -35 }, "color": -1 },
    { "no": 31, "x": 903, "y": 251, "route": { "img": "route_31_1" }, "line": { "x": -33, "y": -32 }, "color": -1 },
    { "no": 32, "x": 824, "y": 328, "route": { "img": "route_32_1" }, "line": { "x": -95, "y": -22 }, "color": -2 },
    { "no": 33, "x": 245, "y": 268, "route": { "img": "route_33_1" }, "line": { "x": -92, "y": -79 }, "color": -1 },
    { "no": 34, "x": 557, "y": 299, "route": { "img": "route_34_1" }, "line": { "x": -187, "y": 2 }, "color": -1 },
    { "no": 35, "x": 678, "y": 133, "route": { "img": "route_35_1" }, "line": { "x": -26, "y": 26 }, "color": -1 },
    {
      "no": 36,
      "x": 788,
      "y": 127,
      "route": { "img": "route_36_1" },
      "line": { "x": 18, "y": 18 },
      "offsets": { "10": { "x": 10, "y": 0 } },
      "color": -1
    },
    { "no": 37, "x": 855, "y": 200, "route": { "img": "route_37_1" }, "line": { "x": -158, "y": -59 }, "color": -1 },
    { "no": 38, "x": 895, "y": 122, "route": { "img": "route_38_1" }, "line": { "x": -33, "y": 18 }, "color": -1 },
    { "no": 39, "x": 990, "y": 194, "route": { "img": "route_39_1" }, "line": { "x": -82, "y": -62 }, "color": -1 },
    { "no": 40, "x": 824, "y": 328, "route": { "img": "route_40_1" }, "line": { "x": -3, "y": -57 }, "color": -2 },
    { "no": 41, "x": 824, "y": 328, "route": { "img": "route_41_1" }, "line": { "x": 26, "y": -63 }, "color": -2 },
    {
      "no": 42,
      "x": 349,
      "y": 356,
      "route": { "img": "route_42_1" },
      "line": { "x": -89, "y": -76 },
      "offsets": { "10": { "x": 8, "y": -5 } },
      "color": -1
    },
    { "no": 43, "x": 115, "y": 158, "color": -3 },
    { "no": 44, "x": 524, "y": 352, "route": { "img": "route_44_1" }, "line": { "x": -89, "y": 1 }, "color": -1 },
    { "no": 45, "x": 658, "y": 397, "route": { "img": "route_45_1" }, "line": { "x": -110, "y": -39 }, "color": -1 },
    { "no": 46, "x": 719, "y": 351, "route": { "img": "route_46_1" }, "line": { "x": -46, "y": 10 }, "color": -1 },
    { "no": 47, "x": 633, "y": 345, "route": { "img": "route_47_1" }, "line": { "x": -85, "y": -12 }, "color": -1 },
    { "no": 48, "x": 272, "y": 477, "route": { "img": "route_48_1" }, "line": { "x": -10, "y": -66 }, "color": -1 },
    {
      "no": 49,
      "x": 349,
      "y": 356,
      "route": { "img": "route_49_1" },
      "line": { "x": -39, "y": 0 },
      "offsets": { "10": { "x": 8, "y": -5 } },
      "color": -1
    },
    { "no": 50, "x": 261, "y": 363, "color": -3 },
    { "no": 51, "x": 769, "y": 375, "route": { "img": "route_51_1" }, "line": { "x": -89, "y": 3 }, "color": -1 },
    {
      "no": 52,
      "x": 809,
      "y": 409,
      "route": { "img": "route_52_1" },
      "line": { "x": -28, "y": -23 },
      "offsets": { "10": { "x": 10, "y": -5 } },
      "color": -1
    },
    { "no": 53, "x": 893, "y": 374, "route": { "img": "route_53_1" }, "line": { "x": -105, "y": -17 }, "color": -2 },
    { "no": 54, "x": 893, "y": 374, "route": { "img": "route_54_1" }, "line": { "x": -72, "y": 16 }, "color": -2 },
    { "no": 55, "x": 769, "y": 375, "route": { "img": "route_55_1" }, "line": { "x": -34, "y": -18 }, "color": -1 },
    { "no": -1, "x": 198, "y": 335 }
  ]
}
